pyroulette/__init__.py
pyroulette/roulette.py
pyroulette-0.0.5.dist-info/METADATA
pyroulette-0.0.5.dist-info/WHEEL
pyroulette-0.0.5.dist-info/top_level.txt
pyroulette-0.0.5.dist-info/RECORD
