Metadata-Version: 2.1
Name: pyroulette
Version: 0.0.5
Summary: A package for exploring roulette strategies.
Home-page: https://git.clfx.cc/mm/roulette
Author: Mathematical Michael
Author-email: consistentbayes@gmail.com
License: MIT
Platform: UNKNOWN
Requires-Python: >=3.6, <4.0
Requires-Dist: dataclasses ; python_version < "3.7"
